pybldc/__init__.py
pybldc/__main__.py
pybldc/logger.py
pybldc/py.typed
pybldc/pybldc.py
pybldc-1.1.0.dist-info/WHEEL
pybldc-1.1.0.dist-info/entry_points.txt
pybldc-1.1.0.dist-info/METADATA
pybldc-1.1.0.dist-info/RECORD
