Metadata-Version: 2.3
Name: pybldc
Version: 1.1.0
Summary: Tool for flashing a VESC via CAN-bus or serial/USB using Python.
Keywords: VESC,bldc,upload,CAN,USB
Author: Kristian Sloth Lauszus
Author-email: Kristian Sloth Lauszus <lauszus@gmail.com>
License:                     GNU GENERAL PUBLIC LICENSE
Classifier: Programming Language :: Python :: 3
Classifier: License :: OSI Approved :: GNU General Public License v3 (GPLv3)
Classifier: Operating System :: OS Independent
Requires-Dist: heatshrink2
Requires-Dist: pyserial
Requires-Dist: python-can>=4.3.0
Requires-Dist: tqdm
Requires-Python: >=3.9
Project-URL: Issues, https://github.com/Lauszus/pybldc/issues
Project-URL: Repository, https://github.com/Lauszus/pybldc
